bpsk_mod/__init__.py
bpsk_mod/demod.py
bpsk_mod/mod.py
bpsk_mod-0.1.0.dist-info/licenses/LICENSE
bpsk_mod-0.1.0.dist-info/METADATA
bpsk_mod-0.1.0.dist-info/WHEEL
bpsk_mod-0.1.0.dist-info/top_level.txt
bpsk_mod-0.1.0.dist-info/RECORD
