Metadata-Version: 2.4
Name: bpsk_mod
Version: 0.1.0
Summary: A simple BPSK modulation and demodulation package
Home-page: https://github.com/vineshey/bpsk
Author: Vinesh V
Author-email: vineshvkavungal@gmail.com
Classifier: Programming Language :: Python :: 3
Classifier: License :: OSI Approved :: MIT License
Classifier: Operating System :: OS Independent
Requires-Python: >=3.6
License-File: LICENSE
Requires-Dist: numpy
Dynamic: author
Dynamic: author-email
Dynamic: classifier
Dynamic: description
Dynamic: description-content-type
Dynamic: home-page
Dynamic: license-file
Dynamic: requires-dist
Dynamic: requires-python
Dynamic: summary
